README.md
setup.py
NaverBlogBackup.egg-info/PKG-INFO
NaverBlogBackup.egg-info/SOURCES.txt
NaverBlogBackup.egg-info/dependency_links.txt
NaverBlogBackup.egg-info/requires.txt
NaverBlogBackup.egg-info/top_level.txt
NaverBlogCrawler/NaverBlogCrawler.py
NaverBlogCrawler/NaverBlogCrawlerTest.py
NaverBlogCrawler/NaverBlogPostCrawler.py
NaverBlogCrawler/SE2PostViewArea.py
NaverBlogCrawler/SE3Component.py
NaverBlogCrawler/__init__.py
NaverBlogCrawler/blogstyle.css
bin/naverblogbackup.py