Metadata-Version: 1.1
Name: NaverBlogBackup
Version: 0.1.3
Summary: Python Crawler for Backup Naver blog posts.
Home-page: https://github.com/Lenir/Naver-Blog-Backup
Author: Lenir
Author-email: 1net1@naver.com
License: BSD License
Keywords: Naver,NaverBlog,Naver-Blog-Backup
Platform: UNKNOWN
Classifier: Development Status :: 4 - Beta
Classifier: Environment :: Console
Classifier: License :: OSI Approved :: BSD License
Classifier: Programming Language :: Python :: 3
Classifier: Topic :: Internet :: WWW/HTTP
Classifier: Topic :: Software Development :: Libraries :: Python Modules
